ModelMerge/__init__.py
ModelMerge/core/.git
ModelMerge/core/__init__.py
ModelMerge/core/log_config.py
ModelMerge/core/models.py
ModelMerge/core/request.py
ModelMerge/core/response.py
ModelMerge/core/utils.py
ModelMerge/core/test/test_base_api.py
ModelMerge/core/test/test_image.py
ModelMerge/core/test/test_payload.py
ModelMerge/models/__init__.py
ModelMerge/models/audio.py
ModelMerge/models/base.py
ModelMerge/models/chatgpt.py
ModelMerge/models/claude.py
ModelMerge/models/duckduckgo.py
ModelMerge/models/gemini.py
ModelMerge/models/groq.py
ModelMerge/models/vertex.py
ModelMerge/plugins/__init__.py
ModelMerge/plugins/arXiv.py
ModelMerge/plugins/config.py
ModelMerge/plugins/image.py
ModelMerge/plugins/registry.py
ModelMerge/plugins/run_python.py
ModelMerge/plugins/today.py
ModelMerge/plugins/websearch.py
ModelMerge/utils/__init__.py
ModelMerge/utils/prompt.py
ModelMerge/utils/scripts.py
modelmerge-1.0.29.dist-info/licenses/LICENSE
modelmerge-1.0.29.dist-info/METADATA
modelmerge-1.0.29.dist-info/WHEEL
modelmerge-1.0.29.dist-info/top_level.txt
modelmerge-1.0.29.dist-info/RECORD
