Metadata-Version: 2.4
Name: modelmerge
Version: 1.0.29
Summary: modelmerge is a multi-large language model API aggregator.
License-File: LICENSE
Requires-Dist: pytz
Requires-Dist: httpx
Requires-Dist: pillow
Requires-Dist: msgspec
Requires-Dist: fastapi
Requires-Dist: PyExecJS
Requires-Dist: requests
Requires-Dist: html2text
Requires-Dist: fake-useragent
Requires-Dist: beautifulsoup4
Requires-Dist: tiktoken==0.6.0
Requires-Dist: lxml-html-clean
Requires-Dist: pdfminer.six==20240706
Requires-Dist: duckduckgo-search==5.3.1
Dynamic: description
Dynamic: description-content-type
Dynamic: license-file
Dynamic: requires-dist
Dynamic: summary
